cwgp/__init__.py
cwgp/cwgp.py
cwgp/grid_search.py
cwgp/kernel.py
cwgp/phi.py
cwgp/transformations.py
CWGP-2.0.7.dist-info/LICENSE
CWGP-2.0.7.dist-info/METADATA
CWGP-2.0.7.dist-info/WHEEL
CWGP-2.0.7.dist-info/top_level.txt
CWGP-2.0.7.dist-info/RECORD
