Metadata-Version: 2.1
Name: CWGP
Version: 2.0.7
Summary: CWGP
Home-page: https://github.com/andy971022/CWGP
Author: Andy Chen
Author-email: andy97_861022_chen@hotmail.com
License: UNKNOWN
Platform: UNKNOWN
Classifier: Programming Language :: Python :: 3
Classifier: License :: OSI Approved :: MIT License
Classifier: Operating System :: OS Independent
Requires-Python: >=3.6
Requires-Dist: autograd
Requires-Dist: scipy (>=1.5.4)
Requires-Dist: tqdm (>=4.56.1)
Requires-Dist: numpy (>=1.18.0)
Requires-Dist: gpy (>=1.9.9)
